{"_type":"export","__export_format":4,"__export_date":"2021-06-26T14:09:57.428Z","__export_source":"insomnia.desktop.app:v2021.3.0","resources":[{"_id":"req_677ea828de0e46bda6963dc45f35c1d1","parentId":"fld_47709ceb60524289b16aedf79d14cd00","modified":1624667812133,"created":1624531786547,"url":"{{ _.base_url }}/api-token-auth/","name":"Obter token","description":"","method":"POST","body":{"mimeType":"application/json","text":"{\n\t\"username\": \"admin\",\n\t\"password\": \"@Suul100pre\"\n}\n"},"parameters":[],"headers":[{"name":"Content-Type","value":"application/json","id":"pair_69528f5c80564a479191d9d69d814193"}],"authentication":{},"metaSortKey":-1624488816399,"isPrivate":false,"settingStoreCookies":true,"settingSendCookies":true,"settingDisableRenderRequestBody":false,"settingEncodeUrl":true,"settingRebuildPath":true,"settingFollowRedirects":"global","_type":"request"},{"_id":"fld_47709ceb60524289b16aedf79d14cd00","parentId":"wrk_65c20c0326354c5aae8cd195c1115531","modified":1624642618630,"created":1624531786546,"name":"Obter Token","description":"","environment":{},"environmentPropertyOrder":null,"metaSortKey":-1624488717836,"_type":"request_group"},{"_id":"wrk_65c20c0326354c5aae8cd195c1115531","parentId":null,"modified":1623438966188,"created":1623438966188,"name":"Insomnia","description":"","scope":"collection","_type":"workspace"},{"_id":"req_5b4ec1da23644c62a296cd1ee1bc2b9a","parentId":"fld_0e3146d83c534610a9ec5c7d8422afbf","modified":1624669595787,"created":1624488816399,"url":"{{ _.base_url }}/pontosturisticos/","name":"Ponto Turístico - List","description":"","method":"GET","body":{},"parameters":[{"name":"nome","value":"Ponto Turístico admin","description":"","id":"pair_1e9b3b3625ee41aca378e1508e512343","disabled":true},{"name":"search","value":"editado","description":"","id":"pair_ecbc0548483e48aebcfcb63fe6260d3d","disabled":true}],"headers":[{"name":"Authorization","value":"{{ _.Token }}","description":"","id":"pair_1d12040e3d1d456f830cbd07edeb6381","disabled":false}],"authentication":{},"metaSortKey":-1624488816399,"isPrivate":false,"settingStoreCookies":true,"settingSendCookies":true,"settingDisableRenderRequestBody":false,"settingEncodeUrl":true,"settingRebuildPath":true,"settingFollowRedirects":"global","_type":"request"},{"_id":"fld_0e3146d83c534610a9ec5c7d8422afbf","parentId":"wrk_65c20c0326354c5aae8cd195c1115531","modified":1624488717785,"created":1624488717785,"name":"Ponto Turístico","description":"","environment":{},"environmentPropertyOrder":null,"metaSortKey":-1624488717786,"_type":"request_group"},{"_id":"req_ad21626a715c49d986fb23dbb742ae95","parentId":"fld_0e3146d83c534610a9ec5c7d8422afbf","modified":1624716327216,"created":1624489316954,"url":"{{ _.base_url }}/pontosturisticos/","name":"Ponto Turístico - create","description":"","method":"POST","body":{"mimeType":"application/json","text":"{\n  \"nome\": \"Ponto turistico PAGINAÇÃO 1\",\n  \"descricao\": \"Teste 2\",\n  \"atracoes\": [\n    {\n      \"nome\": \"Atração Doc 2 (1)\",\n      \"descricao\": \"Ponto turístico\",\n      \"horario_func\": \"Segunda a sexta das 8 as 18\\r\\nSábado e Domingo: 9 as 17\",\n      \"idade_minima\": 12,\n      \"foto\": null\n    },\n\t\t{\n      \"nome\": \"Atração Doc 2 (2)\",\n      \"descricao\": \"Ponto turístico\",\n      \"horario_func\": \"Segunda a sexta das 8 as 18\\r\\nSábado e Domingo: 9 as 17\",\n      \"idade_minima\": 12,\n      \"foto\": null\n    },\n\t\t{\n      \"nome\": \"Atração Doc 2 (3)\",\n      \"descricao\": \"Ponto turístico\",\n      \"horario_func\": \"Segunda a sexta das 8 as 18\\r\\nSábado e Domingo: 9 as 17\",\n      \"idade_minima\": 12,\n      \"foto\": null\n    }\n  ],\n  \"foto\": null,\n  \"comentarios\": [],\n  \"avaliacoes\": [],\n  \"endereco\": {\n    \"linha1\": \"Rua documento, 123 (2)\",\n    \"linha2\": \"Bairro Sta Maria 2\",\n    \"cidade\": \"Cajamar\",\n    \"estado\": \"SP\",\n    \"pais\": \"Brasil\",\n    \"latitude\": 1234,\n    \"longitude\": 4567\n  },\n\t\"doc_identificacao\": {\n\t\t\"description\": \"Descrição do documento (2)\"\n\t},\n\t\"aprovado\": true\n}"},"parameters":[],"headers":[{"name":"Content-Type","value":"application/json","description":"","id":"pair_fa734452bd534c2da7a3d2fd141eeffa"},{"name":"Authorization","value":"{{ _.Token }}","id":"pair_4b2222732e484635b1f6bfbb64866ddf"}],"authentication":{},"metaSortKey":-1624486856094.875,"isPrivate":false,"settingStoreCookies":true,"settingSendCookies":true,"settingDisableRenderRequestBody":false,"settingEncodeUrl":true,"settingRebuildPath":true,"settingFollowRedirects":"global","_type":"request"},{"_id":"req_61893aae36934917a74dcb3daa082e27","parentId":"fld_0e3146d83c534610a9ec5c7d8422afbf","modified":1624664936611,"created":1624489048036,"url":"{{ _.base_url }}/pontosturisticos/15/","name":"Ponto Turístico - read","description":"","method":"GET","body":{},"parameters":[],"headers":[{"name":"Authorization","value":"{{ _.Token }}","description":"","id":"pair_0dc84394e7844c8a9f4ca1b7385cf2ef"}],"authentication":{},"metaSortKey":-1624484895790.75,"isPrivate":false,"settingStoreCookies":true,"settingSendCookies":true,"settingDisableRenderRequestBody":false,"settingEncodeUrl":true,"settingRebuildPath":true,"settingFollowRedirects":"global","_type":"request"},{"_id":"req_53c299d04ac2412bb9122b84f24eb289","parentId":"fld_0e3146d83c534610a9ec5c7d8422afbf","modified":1624665409839,"created":1624489022797,"url":"{{ _.base_url }}/pontosturisticos/15/","name":"Ponto Turístico - update","description":"","method":"PUT","body":{"mimeType":"application/json","text":"{\n  \"id\": 15,\n  \"nome\": \"Ponto turistico varias atrações (Editado PATCH)\",\n  \"descricao\": \"Teste 2 (Editado PATCH)\",\n  \"foto\": null,\n  \"decricao_completa\": \"Ponto turistico varias atrações - Teste 2 (Editado PATCH)\",\n  \"aprovado\": false\n}"},"parameters":[],"headers":[{"name":"Content-Type","value":"application/json","id":"pair_05a37bd9f3af43c1989bce4c8046a359"},{"name":"Authorization","value":"{{ _.Token }}","description":"","id":"pair_a0a9090b4b0c49f59324598054ecbc4e"}],"authentication":{},"metaSortKey":-1624480975182.5,"isPrivate":false,"settingStoreCookies":true,"settingSendCookies":true,"settingDisableRenderRequestBody":false,"settingEncodeUrl":true,"settingRebuildPath":true,"settingFollowRedirects":"global","_type":"request"},{"_id":"req_8f308486044a467e8d7d24e454c11032","parentId":"fld_0e3146d83c534610a9ec5c7d8422afbf","modified":1624505458399,"created":1624489262667,"url":"{{ _.base_url }}/pontosturisticos/3/","name":"Ponto Turístico - delete","description":"","method":"DELETE","body":{},"parameters":[],"headers":[],"authentication":{},"metaSortKey":-1624479995030.4375,"isPrivate":false,"settingStoreCookies":true,"settingSendCookies":true,"settingDisableRenderRequestBody":false,"settingEncodeUrl":true,"settingRebuildPath":true,"settingFollowRedirects":"global","_type":"request"},{"_id":"req_ba0cc37742284b569baa1306091d89ca","parentId":"fld_0e3146d83c534610a9ec5c7d8422afbf","modified":1624665370707,"created":1624491529697,"url":"{{ _.base_url }}/pontosturisticos/15/","name":"Ponto Turístico - patch","description":"","method":"PATCH","body":{"mimeType":"application/json","text":"{\n  \"id\": 15,\n  \"nome\": \"Ponto turistico varias atrações (Editado PATCH)\",\n  \"descricao\": \"Teste 2 (Editado PATCH)\",\n  \"foto\": null,\n  \"decricao_completa\": \"Ponto turistico varias atrações - Teste 2 (Editado PATCH)\",\n  \"aprovado\": false\n}"},"parameters":[],"headers":[{"name":"Content-Type","value":"application/json","id":"pair_05a37bd9f3af43c1989bce4c8046a359"},{"name":"Authorization","value":"{{ _.Token }}","description":"","id":"pair_c2104c9d5f644f84ab3c48b2fdaea5a7"}],"authentication":{},"metaSortKey":-1624479014878.375,"isPrivate":false,"settingStoreCookies":true,"settingSendCookies":true,"settingDisableRenderRequestBody":false,"settingEncodeUrl":true,"settingRebuildPath":true,"settingFollowRedirects":"global","_type":"request"},{"_id":"req_e969688bdbe045d986d7e8a6af436e47","parentId":"fld_0e3146d83c534610a9ec5c7d8422afbf","modified":1624509349220,"created":1624507640808,"url":"{{ _.base_url }}/pontosturisticos/6/denuciar/","name":"Ponto Turístico - denuciar","description":"","method":"POST","body":{"mimeType":"application/json","text":"{\n  \"nome\": \"Ponto Insominia (path)\"\n}"},"parameters":[{"name":"","value":"","description":"","id":"pair_997a800f4bae4f7480d106f7cd8176a2"}],"headers":[{"name":"Content-Type","value":"application/json","id":"pair_05a37bd9f3af43c1989bce4c8046a359"}],"authentication":{},"metaSortKey":-1624478034726.3125,"isPrivate":false,"settingStoreCookies":true,"settingSendCookies":true,"settingDisableRenderRequestBody":false,"settingEncodeUrl":true,"settingRebuildPath":true,"settingFollowRedirects":"global","_type":"request"},{"_id":"req_fcd7fb8d80824bd98b9ebcea2bd1b76c","parentId":"fld_0e3146d83c534610a9ec5c7d8422afbf","modified":1624667734690,"created":1624667265769,"url":"{{ _.base_url }}/pontosturisticos/15/associa_atracoes/","name":"Ponto Turístico - associar atracoes","description":"","method":"POST","body":{"mimeType":"application/json","text":"{\n  \"ids\": [1, 2, 3, 4]\n}"},"parameters":[{"name":"","value":"","description":"","id":"pair_997a800f4bae4f7480d106f7cd8176a2"}],"headers":[{"name":"Content-Type","value":"application/json","id":"pair_05a37bd9f3af43c1989bce4c8046a359"},{"name":"Authorization","value":"{{ _.Token }}","description":"","id":"pair_08be6a45432947e28543eb051ee52587"}],"authentication":{},"metaSortKey":-1624477544650.2812,"isPrivate":false,"settingStoreCookies":true,"settingSendCookies":true,"settingDisableRenderRequestBody":false,"settingEncodeUrl":true,"settingRebuildPath":true,"settingFollowRedirects":"global","_type":"request"},{"_id":"req_95cdf2b735224eaa8b1d932f8fadb07d","parentId":"fld_0a112f1f13884237817e75b51e7f8a53","modified":1624539201557,"created":1624491041042,"url":"{{ _.base_url }}/atracoes/","name":"Ponto Turístico - List","description":"","method":"GET","body":{},"parameters":[],"headers":[{"name":"Authorization","value":"{{ _.Token }}","description":"","id":"pair_e1d0fe06d9ef487895bb15e862bda415"}],"authentication":{},"metaSortKey":-1624488816399,"isPrivate":false,"settingStoreCookies":true,"settingSendCookies":true,"settingDisableRenderRequestBody":false,"settingEncodeUrl":true,"settingRebuildPath":true,"settingFollowRedirects":"global","_type":"request"},{"_id":"fld_0a112f1f13884237817e75b51e7f8a53","parentId":"wrk_65c20c0326354c5aae8cd195c1115531","modified":1624491041040,"created":1624491041040,"name":"Atração","description":"","environment":{},"environmentPropertyOrder":null,"metaSortKey":-1624480908848,"_type":"request_group"},{"_id":"req_5dd6493c6f684ba0bedc2a8fe2d6d06b","parentId":"fld_0a112f1f13884237817e75b51e7f8a53","modified":1624539207390,"created":1624491041048,"url":"{{ _.base_url }}/atracoes/","name":"Ponto Turístico - create","description":"","method":"POST","body":{"mimeType":"application/json","text":"{\n\t\"nome\": \"Ponto turístico 2\",\n\t\"descricao\": \"Segundo ponto turístico\",\n\t\"horario_func\": \"Segunda a sexta das 8 as 18\\r\\nSábado e Domingo: 9 as 17\",\n\t\"idade_minima\": 12\n}"},"parameters":[],"headers":[{"name":"Content-Type","value":"application/json","id":"pair_4b2222732e484635b1f6bfbb64866ddf"}],"authentication":{},"metaSortKey":-1624486856094.875,"isPrivate":false,"settingStoreCookies":true,"settingSendCookies":true,"settingDisableRenderRequestBody":false,"settingEncodeUrl":true,"settingRebuildPath":true,"settingFollowRedirects":"global","_type":"request"},{"_id":"req_efc919650a984aac9908ba54fc9be1ce","parentId":"fld_0a112f1f13884237817e75b51e7f8a53","modified":1624539210408,"created":1624491041045,"url":"{{ _.base_url }}/atracoes/2/","name":"Ponto Turístico - read","description":"","method":"GET","body":{},"parameters":[],"headers":[],"authentication":{},"metaSortKey":-1624484895790.75,"isPrivate":false,"settingStoreCookies":true,"settingSendCookies":true,"settingDisableRenderRequestBody":false,"settingEncodeUrl":true,"settingRebuildPath":true,"settingFollowRedirects":"global","_type":"request"},{"_id":"req_b9394a95ec61487baa201e37e229de73","parentId":"fld_0a112f1f13884237817e75b51e7f8a53","modified":1624539213378,"created":1624491041044,"url":"{{ _.base_url }}/atracoes/1/","name":"Ponto Turístico - update","description":"","method":"PUT","body":{"mimeType":"multipart/form-data","params":[{"name":"nome","value":"Ponto turístico 2 (Atualizado2)","id":"pair_3681ea4421d44aa9bea346191aac585c"}]},"parameters":[],"headers":[{"name":"Content-Type","value":"multipart/form-data","id":"pair_05a37bd9f3af43c1989bce4c8046a359"}],"authentication":{},"metaSortKey":-1624480975182.5,"isPrivate":false,"settingStoreCookies":true,"settingSendCookies":true,"settingDisableRenderRequestBody":false,"settingEncodeUrl":true,"settingRebuildPath":true,"settingFollowRedirects":"global","_type":"request"},{"_id":"req_d7c5995195d94c42874249a12aadbc79","parentId":"fld_0a112f1f13884237817e75b51e7f8a53","modified":1624539216732,"created":1624491041046,"url":"{{ _.base_url }}/atracoes/3/","name":"Ponto Turístico - delete","description":"","method":"DELETE","body":{},"parameters":[],"headers":[],"authentication":{},"metaSortKey":-1624477054574.25,"isPrivate":false,"settingStoreCookies":true,"settingSendCookies":true,"settingDisableRenderRequestBody":false,"settingEncodeUrl":true,"settingRebuildPath":true,"settingFollowRedirects":"global","_type":"request"},{"_id":"req_876427f79a9d47fd830ad5024454cbb6","parentId":"fld_0a112f1f13884237817e75b51e7f8a53","modified":1624539234142,"created":1624491476004,"url":"{{ _.base_url }}/atracoes/2/","name":"Ponto Turístico - patch","description":"","method":"PATCH","body":{"mimeType":"multipart/form-data","params":[{"name":"nome","value":"Ponto turístico 2 (Atualizado2)","description":"","id":"pair_57e137b037674f24bd6c2d3361ac9169"}]},"parameters":[],"headers":[{"name":"Content-Type","value":"multipart/form-data","id":"pair_1008dbb69cf94702b02e9ec8c8a4ce65"},{"name":"Authorization","value":"{{ _.Token }}","description":"","id":"pair_6fa0791b4a3145fc938a8db44e0abdfe"}],"authentication":{},"metaSortKey":-1624475094270.125,"isPrivate":false,"settingStoreCookies":true,"settingSendCookies":true,"settingDisableRenderRequestBody":false,"settingEncodeUrl":true,"settingRebuildPath":true,"settingFollowRedirects":"global","_type":"request"},{"_id":"req_6b5d2f4805c943d08fc5b551f7839ee9","parentId":"fld_d0ff9007b1844ccab7237ae18c8717c5","modified":1624716415167,"created":1624492345442,"url":"{{ _.base_url }}/enderecos/","name":"Ponto Turístico - List","description":"","method":"GET","body":{},"parameters":[],"headers":[{"name":"Authorization","value":"{{ _.Token }}","description":"","id":"pair_57f714ff52e34d15b71f0058e8bd406e"}],"authentication":{},"metaSortKey":-1624488816399,"isPrivate":false,"settingStoreCookies":true,"settingSendCookies":true,"settingDisableRenderRequestBody":false,"settingEncodeUrl":true,"settingRebuildPath":true,"settingFollowRedirects":"global","_type":"request"},{"_id":"fld_d0ff9007b1844ccab7237ae18c8717c5","parentId":"wrk_65c20c0326354c5aae8cd195c1115531","modified":1624492345440,"created":1624492345440,"name":"Endereço","description":"","environment":{},"environmentPropertyOrder":null,"metaSortKey":-1624477004379,"_type":"request_group"},{"_id":"req_301d323f361f4a11a143f6e83fcceee8","parentId":"fld_d0ff9007b1844ccab7237ae18c8717c5","modified":1624492496521,"created":1624492345448,"url":"{{ _.base_url }}/endereco/","name":"Ponto Turístico - create","description":"","method":"POST","body":{"mimeType":"application/json","text":"  {\n    \"id\": 1,\n    \"linha1\": \"Rua Tres, 123\",\n    \"linha2\": \"Bairro Sta Maria 2\",\n    \"cidade\": \"Cajamar\",\n    \"estado\": \"SP\",\n    \"pais\": \"Brasil\",\n    \"latitude\": 1234,\n    \"longitude\": 4567\n  }"},"parameters":[],"headers":[{"name":"Content-Type","value":"application/json","id":"pair_4b2222732e484635b1f6bfbb64866ddf"}],"authentication":{},"metaSortKey":-1624486856094.875,"isPrivate":false,"settingStoreCookies":true,"settingSendCookies":true,"settingDisableRenderRequestBody":false,"settingEncodeUrl":true,"settingRebuildPath":true,"settingFollowRedirects":"global","_type":"request"},{"_id":"req_4461b51d2c964bb0b0b94c715eefda80","parentId":"fld_d0ff9007b1844ccab7237ae18c8717c5","modified":1624492460196,"created":1624492345445,"url":"{{ _.base_url }}/endereco/2/","name":"Ponto Turístico - read","description":"","method":"GET","body":{"mimeType":"application/json","text":""},"parameters":[],"headers":[{"name":"Content-Type","value":"application/json"}],"authentication":{},"metaSortKey":-1624484895790.75,"isPrivate":false,"settingStoreCookies":true,"settingSendCookies":true,"settingDisableRenderRequestBody":false,"settingEncodeUrl":true,"settingRebuildPath":true,"settingFollowRedirects":"global","_type":"request"},{"_id":"req_672701d3a15b4ff5816098746d314ee8","parentId":"fld_d0ff9007b1844ccab7237ae18c8717c5","modified":1624492479756,"created":1624492345443,"url":"{{ _.base_url }}/endereco/1/","name":"Ponto Turístico - update","description":"","method":"PUT","body":{"mimeType":"application/json","text":"  {\n    \"id\": 1,\n    \"linha1\": \"Rua Dois, 123 (Editado)\",\n    \"linha2\": \"Bairro Sta Maria 2\",\n    \"cidade\": \"Cajamar\",\n    \"estado\": \"SP\",\n    \"pais\": \"Brasil\",\n    \"latitude\": 1234,\n    \"longitude\": 4567\n  }"},"parameters":[],"headers":[{"name":"Content-Type","value":"application/json","id":"pair_05a37bd9f3af43c1989bce4c8046a359"}],"authentication":{},"metaSortKey":-1624480975182.5,"isPrivate":false,"settingStoreCookies":true,"settingSendCookies":true,"settingDisableRenderRequestBody":false,"settingEncodeUrl":true,"settingRebuildPath":true,"settingFollowRedirects":"global","_type":"request"},{"_id":"req_88ea715d484646ce92febdcc855fd12f","parentId":"fld_d0ff9007b1844ccab7237ae18c8717c5","modified":1624492376427,"created":1624492345447,"url":"{{ _.base_url }}/endereco/3/","name":"Ponto Turístico - delete","description":"","method":"DELETE","body":{},"parameters":[],"headers":[],"authentication":{},"metaSortKey":-1624477054574.25,"isPrivate":false,"settingStoreCookies":true,"settingSendCookies":true,"settingDisableRenderRequestBody":false,"settingEncodeUrl":true,"settingRebuildPath":true,"settingFollowRedirects":"global","_type":"request"},{"_id":"req_727c97be9e0f4d048c01f831301da1ed","parentId":"fld_d0ff9007b1844ccab7237ae18c8717c5","modified":1624492383299,"created":1624492345450,"url":"{{ _.base_url }}/endereco/2/","name":"Ponto Turístico - patch","description":"","method":"PATCH","body":{"mimeType":"multipart/form-data","params":[{"name":"nome","value":"Ponto turístico 2 (Atualizado2)","description":"","id":"pair_57e137b037674f24bd6c2d3361ac9169"}]},"parameters":[],"headers":[{"name":"Content-Type","value":"multipart/form-data","id":"pair_1008dbb69cf94702b02e9ec8c8a4ce65"}],"authentication":{},"metaSortKey":-1624475094270.125,"isPrivate":false,"settingStoreCookies":true,"settingSendCookies":true,"settingDisableRenderRequestBody":false,"settingEncodeUrl":true,"settingRebuildPath":true,"settingFollowRedirects":"global","_type":"request"},{"_id":"req_baa7fcb6b5ef4a4ebd44af1051708f21","parentId":"fld_84cf17a7991f4c63bfbaf24d9ec921ed","modified":1624716439625,"created":1624503371340,"url":"{{ _.base_url }}/comentarios/","name":"Ponto Turístico - List","description":"","method":"GET","body":{},"parameters":[],"headers":[{"name":"Authorization","value":"{{ _.Token }}","description":"","id":"pair_b1a3b311d19b48b2a5eb6e2a7131fbea"}],"authentication":{},"metaSortKey":-1624488816399,"isPrivate":false,"settingStoreCookies":true,"settingSendCookies":true,"settingDisableRenderRequestBody":false,"settingEncodeUrl":true,"settingRebuildPath":true,"settingFollowRedirects":"global","_type":"request"},{"_id":"fld_84cf17a7991f4c63bfbaf24d9ec921ed","parentId":"wrk_65c20c0326354c5aae8cd195c1115531","modified":1624503371339,"created":1624503371339,"name":"Comentário","description":"","environment":{},"environmentPropertyOrder":null,"metaSortKey":-1624475052144.5,"_type":"request_group"},{"_id":"req_427c50d34ee143bda690af8154148606","parentId":"fld_84cf17a7991f4c63bfbaf24d9ec921ed","modified":1624716486152,"created":1624503371347,"url":"{{ _.base_url }}/comentarios/","name":"Ponto Turístico - create","description":"","method":"POST","body":{"mimeType":"application/json","text":"{\n\t\"usuario\": 1,\n\t\"comentario\": \"Comentario Insominia\",\n\t\"aprovado\": true\n}"},"parameters":[],"headers":[{"name":"Content-Type","value":"application/json","id":"pair_4b2222732e484635b1f6bfbb64866ddf"},{"name":"Authorization","value":"{{ _.Token }}","description":"","id":"pair_9768a17093294263acff56d831ed9118"}],"authentication":{},"metaSortKey":-1624486856094.875,"isPrivate":false,"settingStoreCookies":true,"settingSendCookies":true,"settingDisableRenderRequestBody":false,"settingEncodeUrl":true,"settingRebuildPath":true,"settingFollowRedirects":"global","_type":"request"},{"_id":"req_61de4bc310de4937933a30e1479a214b","parentId":"fld_84cf17a7991f4c63bfbaf24d9ec921ed","modified":1624503483978,"created":1624503371344,"url":"{{ _.base_url }}/comentarios/2/","name":"Ponto Turístico - read","description":"","method":"GET","body":{"mimeType":"application/json","text":""},"parameters":[],"headers":[{"name":"Content-Type","value":"application/json","id":"pair_a973825c00fd433c9dedee494d9842a3"}],"authentication":{},"metaSortKey":-1624484895790.75,"isPrivate":false,"settingStoreCookies":true,"settingSendCookies":true,"settingDisableRenderRequestBody":false,"settingEncodeUrl":true,"settingRebuildPath":true,"settingFollowRedirects":"global","_type":"request"},{"_id":"req_6761f37702644298a145ccaa73101b38","parentId":"fld_84cf17a7991f4c63bfbaf24d9ec921ed","modified":1624503509973,"created":1624503371342,"url":"{{ _.base_url }}/comentarios/1/","name":"Ponto Turístico - update","description":"","method":"PUT","body":{"mimeType":"application/json","text":"{\n    \"id\": 1,\n    \"usuario\": 1,\n    \"comentario\": \"Comentario 1 (Editado)\",\n    \"data\": \"2021-06-23T17:32:26.545400-03:00\",\n    \"aprovado\": true\n  }"},"parameters":[],"headers":[{"name":"Content-Type","value":"application/json","id":"pair_05a37bd9f3af43c1989bce4c8046a359"}],"authentication":{},"metaSortKey":-1624480975182.5,"isPrivate":false,"settingStoreCookies":true,"settingSendCookies":true,"settingDisableRenderRequestBody":false,"settingEncodeUrl":true,"settingRebuildPath":true,"settingFollowRedirects":"global","_type":"request"},{"_id":"req_d52e61a9e0c44319aaf7c0cf540a485b","parentId":"fld_84cf17a7991f4c63bfbaf24d9ec921ed","modified":1624503536460,"created":1624503371346,"url":"{{ _.base_url }}/comentarios/3/","name":"Ponto Turístico - delete","description":"","method":"DELETE","body":{},"parameters":[],"headers":[],"authentication":{},"metaSortKey":-1624477054574.25,"isPrivate":false,"settingStoreCookies":true,"settingSendCookies":true,"settingDisableRenderRequestBody":false,"settingEncodeUrl":true,"settingRebuildPath":true,"settingFollowRedirects":"global","_type":"request"},{"_id":"req_0036a1d0099c49d7b430fe64f3cd87c2","parentId":"fld_84cf17a7991f4c63bfbaf24d9ec921ed","modified":1624503602267,"created":1624503371351,"url":"{{ _.base_url }}/comentarios/2/","name":"Ponto Turístico - patch","description":"","method":"PATCH","body":{"mimeType":"application/json","text":"{\n\t  \"data\": \"2021-06-23T21:55:46.089923-03:00\"\n}"},"parameters":[],"headers":[{"name":"Content-Type","value":"application/json","id":"pair_1008dbb69cf94702b02e9ec8c8a4ce65"}],"authentication":{},"metaSortKey":-1624475094270.125,"isPrivate":false,"settingStoreCookies":true,"settingSendCookies":true,"settingDisableRenderRequestBody":false,"settingEncodeUrl":true,"settingRebuildPath":true,"settingFollowRedirects":"global","_type":"request"},{"_id":"req_4d720e7fe1324974a61c9af59959fb0b","parentId":"fld_7660a08980de4b278af0b96184aa2f05","modified":1624716534208,"created":1624504330535,"url":"{{ _.base_url }}/avaliacoes/","name":"Ponto Turístico - List","description":"","method":"GET","body":{"mimeType":"application/json","text":"{\n\t\"id\": 1,\n\t\"usuario\": 1,\n\t\"comentario\": \"Primeira avaliação\",\n\t\"nota\": \"4.75\",\n\t\"data\": \"2021-06-23T17:43:00.779137-03:00\"\n}\n"},"parameters":[],"headers":[{"name":"Content-Type","value":"application/json","id":"pair_69528f5c80564a479191d9d69d814193"},{"name":"Authorization","value":"{{ _.Token }}","description":"","id":"pair_f7e1569406a94a378a45b523c7486c79"}],"authentication":{},"metaSortKey":-1624488816399,"isPrivate":false,"settingStoreCookies":true,"settingSendCookies":true,"settingDisableRenderRequestBody":false,"settingEncodeUrl":true,"settingRebuildPath":true,"settingFollowRedirects":"global","_type":"request"},{"_id":"fld_7660a08980de4b278af0b96184aa2f05","parentId":"wrk_65c20c0326354c5aae8cd195c1115531","modified":1624504330533,"created":1624504330533,"name":"Avaliação","description":"","environment":{},"environmentPropertyOrder":null,"metaSortKey":-1624474076027.25,"_type":"request_group"},{"_id":"req_326f0863b17c4063b1efeaa2b36cb746","parentId":"fld_7660a08980de4b278af0b96184aa2f05","modified":1624716545150,"created":1624504330541,"url":"{{ _.base_url }}/avaliacoes/","name":"Ponto Turístico - create","description":"","method":"POST","body":{"mimeType":"application/json","text":"{\n    \"id\": 1,\n    \"usuario\": 1,\n    \"comentario\": \"Primeira avaliação Insominia\",\n    \"nota\": \"4.75\",\n    \"data\": \"2021-06-23T17:43:00.779137-03:00\"\n  }"},"parameters":[],"headers":[{"name":"Content-Type","value":"application/json","id":"pair_4b2222732e484635b1f6bfbb64866ddf"},{"name":"Authorization","value":"{{ _.Token }}","description":"","id":"pair_18f0488b54f840eb8ddd6222696b7d50"}],"authentication":{},"metaSortKey":-1624486856094.875,"isPrivate":false,"settingStoreCookies":true,"settingSendCookies":true,"settingDisableRenderRequestBody":false,"settingEncodeUrl":true,"settingRebuildPath":true,"settingFollowRedirects":"global","_type":"request"},{"_id":"req_71e98465de2b4b9484ed7fcb5c6e4191","parentId":"fld_7660a08980de4b278af0b96184aa2f05","modified":1624504551370,"created":1624504330538,"url":"{{ _.base_url }}/avaliacoes/3/","name":"Ponto Turístico - read","description":"","method":"GET","body":{"mimeType":"application/json","text":""},"parameters":[],"headers":[{"name":"Content-Type","value":"application/json","id":"pair_a973825c00fd433c9dedee494d9842a3"}],"authentication":{},"metaSortKey":-1624484895790.75,"isPrivate":false,"settingStoreCookies":true,"settingSendCookies":true,"settingDisableRenderRequestBody":false,"settingEncodeUrl":true,"settingRebuildPath":true,"settingFollowRedirects":"global","_type":"request"},{"_id":"req_f336825dafae4ebf96a68a722d7af4ad","parentId":"fld_7660a08980de4b278af0b96184aa2f05","modified":1624504596774,"created":1624504330536,"url":"{{ _.base_url }}/avaliacoes/3/","name":"Ponto Turístico - update","description":"","method":"PUT","body":{"mimeType":"application/json","text":"{\n    \"id\": 1,\n    \"usuario\": 1,\n    \"comentario\": \"Primeira avaliação (PUT)\",\n    \"nota\": \"4.85\",\n    \"data\": \"2021-06-23T17:43:00.779137-03:00\"\n  }"},"parameters":[],"headers":[{"name":"Content-Type","value":"application/json","id":"pair_05a37bd9f3af43c1989bce4c8046a359"}],"authentication":{},"metaSortKey":-1624480975182.5,"isPrivate":false,"settingStoreCookies":true,"settingSendCookies":true,"settingDisableRenderRequestBody":false,"settingEncodeUrl":true,"settingRebuildPath":true,"settingFollowRedirects":"global","_type":"request"},{"_id":"req_a83841a9c2c64246835736948d94aecd","parentId":"fld_7660a08980de4b278af0b96184aa2f05","modified":1624504605832,"created":1624504330540,"url":"{{ _.base_url }}/avaliacoes/3/","name":"Ponto Turístico - delete","description":"","method":"DELETE","body":{},"parameters":[],"headers":[],"authentication":{},"metaSortKey":-1624477054574.25,"isPrivate":false,"settingStoreCookies":true,"settingSendCookies":true,"settingDisableRenderRequestBody":false,"settingEncodeUrl":true,"settingRebuildPath":true,"settingFollowRedirects":"global","_type":"request"},{"_id":"req_5fa8291bf1014f88a98dad86976ac0e8","parentId":"fld_7660a08980de4b278af0b96184aa2f05","modified":1624504684244,"created":1624504330542,"url":"{{ _.base_url }}/comentarios/2/","name":"Ponto Turístico - patch","description":"","method":"PATCH","body":{"mimeType":"application/json","text":"{\n\t  \"comentario\": \"Cometário (PATCH)\"\n}"},"parameters":[],"headers":[{"name":"Content-Type","value":"application/json","id":"pair_1008dbb69cf94702b02e9ec8c8a4ce65"}],"authentication":{},"metaSortKey":-1624475094270.125,"isPrivate":false,"settingStoreCookies":true,"settingSendCookies":true,"settingDisableRenderRequestBody":false,"settingEncodeUrl":true,"settingRebuildPath":true,"settingFollowRedirects":"global","_type":"request"},{"_id":"env_9001fec7653cdbcc7c0b5f7007524b8eb0376b22","parentId":"wrk_65c20c0326354c5aae8cd195c1115531","modified":1624716300825,"created":1623438966228,"name":"Base Environment","data":{"_base_url":"http://127.0.0.1:8000","base_url":"https://aplucas-pontos-turisticos.herokuapp.com","Token":"Token 33b1b5a886b7aad185acdd1cc188a734c22e3c70"},"dataPropertyOrder":{"&":["_base_url","base_url","Token"]},"color":null,"isPrivate":false,"metaSortKey":1623438966228,"_type":"environment"},{"_id":"jar_9001fec7653cdbcc7c0b5f7007524b8eb0376b22","parentId":"wrk_65c20c0326354c5aae8cd195c1115531","modified":1623438966230,"created":1623438966230,"name":"Default Jar","cookies":[],"_type":"cookie_jar"},{"_id":"spc_a150452ded624a3e89c5ccc766ab245d","parentId":"wrk_65c20c0326354c5aae8cd195c1115531","modified":1623438966191,"created":1623438966191,"fileName":"Insomnia","contents":"","contentType":"yaml","_type":"api_spec"}]}